swarm_controller/__init__.py
swarm_controller/core.py
swarm_controller/node.py
swarm_controller/swarm.py
swarm_controller-1.0.4.dist-info/entry_points.txt
swarm_controller-1.0.4.dist-info/LICENSE
swarm_controller-1.0.4.dist-info/WHEEL
swarm_controller-1.0.4.dist-info/METADATA
swarm_controller-1.0.4.dist-info/RECORD
