Metadata-Version: 2.1
Name: swarm-controller
Version: 1.0.4
Summary: Cluster bootstrapping for Docker Swarm on AWS
Home-page: https://github.com/jaredvacanti/swarm-controller
License: MIT
Keywords: docker,docker-swarm
Author: Jared Vacanti
Author-email: jaredvacanti@gmail.com
Requires-Python: >=3.6,<4.0
Classifier: License :: OSI Approved :: MIT License
Classifier: Programming Language :: Python :: 3
Classifier: Programming Language :: Python :: 3.6
Classifier: Programming Language :: Python :: 3.7
Requires-Dist: boto3 (>=1.10.12,<2.0.0)
Requires-Dist: click (>=7.0,<8.0)
Requires-Dist: docker (>=4.1.0,<5.0.0)
Requires-Dist: paramiko (>=2.6,<3.0)
Requires-Dist: requests (>=2.22.0,<3.0.0)
Project-URL: Repository, https://github.com/jaredvacanti/swarm-controller
